threadPlotter/DirectAuthoringGenerator.py
threadPlotter/ThreadPlotter.py
threadPlotter/__init__.py
threadPlotter/updateColor.py
threadPlotter/TP_punchneedle/GridImgConverter.py
threadPlotter/TP_punchneedle/__init__.py
threadPlotter/TP_punchneedle/embroideryCalculation.py
threadPlotter/TP_punchneedle/embroidery_thread_color.csv
threadPlotter/TP_punchneedle/threadColor.pkl
threadPlotter/TP_punchneedle/threadColorManagement.py
threadPlotter/TP_structure/PathList.py
threadPlotter/TP_structure/Point.py
threadPlotter/TP_structure/PunchGroup.py
threadPlotter/TP_structure/__init__.py
threadPlotter/TP_utils/__init__.py
threadPlotter/TP_utils/basic.py
threadPlotter/TP_utils/clipperHelper.py
threadPlotter/TP_utils/fillPath.py
threadPlotter/TP_utils/shapeEditing.py
threadPlotter/TP_utils/svg.py
threadPlotter-0.0.2b2.dist-info/DESCRIPTION.rst
threadPlotter-0.0.2b2.dist-info/METADATA
threadPlotter-0.0.2b2.dist-info/RECORD
threadPlotter-0.0.2b2.dist-info/WHEEL
threadPlotter-0.0.2b2.dist-info/metadata.json
threadPlotter-0.0.2b2.dist-info/top_level.txt
