Metadata-Version: 2.0
Name: threadPlotter
Version: 0.0.2b2
Summary: a toolkit for designing plotter-compatible embroidery patterns
Home-page: http://eyesofpanda.com/projects/thread_plotter/
Author: Shiqing Licia He
Author-email: heslicia@umich.edu
License: MIT
Project-URL: Documentation, https://github.com/LiciaHe/threadPlotter
Project-URL: Project Site, http://eyesofpanda.com/projects/thread_plotter/
Project-URL: Source, https://github.com/LiciaHe/threadPlotter
Keywords: punch needle embroidery; plotter embroidery
Platform: UNKNOWN
Classifier: Development Status :: 4 - Beta
Classifier: Intended Audience :: Manufacturing
Classifier: Topic :: Adaptive Technologies
Classifier: License :: OSI Approved :: MIT License
Classifier: Programming Language :: Python :: 3.6
Classifier: Programming Language :: Python :: 3.7
Classifier: Programming Language :: Python :: 3.8
Requires-Python: ~=3.6
Requires-Dist: Pillow (>=7.1.2)
Requires-Dist: bs4 (>=0.0.1)
Requires-Dist: numpy
Requires-Dist: pyclipper (>=1.1.0.post3)
Requires-Dist: scipy
Requires-Dist: svgpathtools (>=1.3.3)
